django_admin_row_actions/__init__.py
django_admin_row_actions/admin.py
django_admin_row_actions/components.py
django_admin_row_actions/locale/ru_RU/LC_MESSAGES/django.po
django_admin_row_actions/locale/zh_Hant/LC_MESSAGES/django.mo
django_admin_row_actions/locale/zh_Hant/LC_MESSAGES/django.po
django_admin_row_actions/static/css/jquery.dropdown.min.css
django_admin_row_actions/static/js/jquery.dropdown.js
django_admin_row_actions/static/js/jquery.dropdown.min.js
django_admin_row_actions/templates/django_admin_row_actions/dropdown.html
django_admin_row_actions/utils.py
django_admin_row_actions/views.py
django_admin_row_actions-0.10.0.dist-info/LICENSE
django_admin_row_actions-0.10.0.dist-info/METADATA
django_admin_row_actions-0.10.0.dist-info/WHEEL
django_admin_row_actions-0.10.0.dist-info/RECORD
