Metadata-Version: 2.1
Name: django-admin-row-actions
Version: 0.10.0
Summary: Add action buttons to individual rows in the Django Admin
Home-page: https://pypi.org/project/django-admin-row-actions/
Author: Andy Baker
Author-email: andy@andybak.net
Classifier: Programming Language :: Python :: 2
Classifier: Programming Language :: Python :: 2.7
Classifier: Programming Language :: Python :: 3
Classifier: Programming Language :: Python :: 3.4
Classifier: Programming Language :: Python :: 3.5
Classifier: Programming Language :: Python :: 3.6
Classifier: Programming Language :: Python :: 3.7
Classifier: Programming Language :: Python :: 3.8
Classifier: Programming Language :: Python :: 3.9
Classifier: Programming Language :: Python :: 3.10
Classifier: Programming Language :: Python :: 3.11
Project-URL: Repository, https://github.com/DjangoAdminHackers/django-admin-row-actions
